Metadata-Version: 2.4
Name: rubricgenerator-mcp-server
Version: 0.0.2
Summary: Add your description here
Requires-Python: >=3.11
Requires-Dist: arxiv==2.1.3
Requires-Dist: build>=1.2.2.post1
Requires-Dist: chromadb==0.6.3
Requires-Dist: deepl==1.21.1
Requires-Dist: docx2txt==0.8
Requires-Dist: dotenv>=0.9.9
Requires-Dist: faiss-cpu==1.10.0
Requires-Dist: flashrank==0.2.10
Requires-Dist: google-search-results==2.4.2
Requires-Dist: grandalf==0.8
Requires-Dist: huggingface-hub==0.29.3
Requires-Dist: jupyter==1.1.1
Requires-Dist: kiwipiepy==0.20.4
Requires-Dist: konlpy==0.6.0
Requires-Dist: langchain==0.3.21
Requires-Dist: langchain-anthropic==0.3.10
Requires-Dist: langchain-azure-ai==0.1.2
Requires-Dist: langchain-chroma==0.2.2
Requires-Dist: langchain-cohere==0.4.3
Requires-Dist: langchain-community==0.3.20
Requires-Dist: langchain-core==0.3.46
Requires-Dist: langchain-elasticsearch==0.3.2
Requires-Dist: langchain-experimental==0.3.4
Requires-Dist: langchain-google-genai==2.1.0
Requires-Dist: langchain-huggingface==0.1.2
Requires-Dist: langchain-milvus==0.1.8
Requires-Dist: langchain-ollama==0.2.3
Requires-Dist: langchain-openai==0.3.9
Requires-Dist: langchain-teddynote==0.3.44
Requires-Dist: langchain-text-splitters==0.3.7
Requires-Dist: langchainhub==0.1.21
Requires-Dist: langgraph==0.3.18
Requires-Dist: langsmith==0.3.18
Requires-Dist: lark==1.2.2
Requires-Dist: llama-index-core==0.11.23
Requires-Dist: llama-index-readers-file==0.2.2
Requires-Dist: llama-parse==0.6.4.post1
Requires-Dist: lxml==5.3.1
Requires-Dist: matplotlib==3.10.1
Requires-Dist: mcp>=1.9.3
Requires-Dist: mypy==1.15.0
Requires-Dist: nest-asyncio==1.6.0
Requires-Dist: notebook==7.3.3
Requires-Dist: open-clip-torch==2.31.0
Requires-Dist: openai==1.67.0
Requires-Dist: openai-agents>=0.0.12
Requires-Dist: pandas==2.2.3
Requires-Dist: pdfminer-six==20231228
Requires-Dist: pdfplumber==0.11.5
Requires-Dist: pillow==10.4.0
Requires-Dist: pinecone==5.4.2
Requires-Dist: protobuf==3.20.3
Requires-Dist: pydantic==2.10.6
Requires-Dist: pymilvus==2.5.5
Requires-Dist: pymupdf==1.25.4
Requires-Dist: pymupdf4llm==0.0.17
Requires-Dist: pypdf==4.3.1
Requires-Dist: python-dotenv==1.0.1
Requires-Dist: ragas==0.2.14
Requires-Dist: rank-bm25==0.2.2
Requires-Dist: rapidocr-onnxruntime==1.4.4
Requires-Dist: redis==5.2.1
Requires-Dist: rouge-score==0.1.2
Requires-Dist: scikit-learn==1.6.1
Requires-Dist: seaborn==0.13.2
Requires-Dist: sqlalchemy==2.0.39
Requires-Dist: streamlit==1.43.2
Requires-Dist: tenacity==8.5.0
Requires-Dist: tiktoken==0.9.0
Requires-Dist: torch==2.6.0
Requires-Dist: torchvision==0.21.0
Requires-Dist: twine>=6.1.0
Requires-Dist: unstructured==0.17.0
Requires-Dist: wikipedia==1.4.0
